flet/__init__.py
flet/app.py
flet/cli.py
flet/flet_socket_server.py
flet/matplotlib_chart.py
flet/plotly_chart.py
flet/pyodide_connection.py
flet/version.py
flet/ads/__init__.py
flet/auth/__init__.py
flet/auth/authorization.py
flet/auth/group.py
flet/auth/oauth_provider.py
flet/auth/oauth_token.py
flet/auth/user.py
flet/auth/providers/__init__.py
flet/auth/providers/auth0_oauth_provider.py
flet/auth/providers/azure_oauth_provider.py
flet/auth/providers/github_oauth_provider.py
flet/auth/providers/google_oauth_provider.py
flet/canvas/__init__.py
flet/core/adaptive_control.py
flet/core/alert_dialog.py
flet/core/alignment.py
flet/core/animated_switcher.py
flet/core/animation.py
flet/core/app_bar.py
flet/core/audio.py
flet/core/audio_recorder.py
flet/core/auto_complete.py
flet/core/autofill_group.py
flet/core/badge.py
flet/core/banner.py
flet/core/blur.py
flet/core/border.py
flet/core/border_radius.py
flet/core/bottom_app_bar.py
flet/core/bottom_sheet.py
flet/core/box.py
flet/core/button.py
flet/core/buttons.py
flet/core/card.py
flet/core/checkbox.py
flet/core/chip.py
flet/core/circle_avatar.py
flet/core/client_storage.py
flet/core/colors.py
flet/core/column.py
flet/core/connection.py
flet/core/constrained_control.py
flet/core/container.py
flet/core/control.py
flet/core/control_event.py
flet/core/cupertino_action_sheet.py
flet/core/cupertino_action_sheet_action.py
flet/core/cupertino_activity_indicator.py
flet/core/cupertino_alert_dialog.py
flet/core/cupertino_app_bar.py
flet/core/cupertino_bottom_sheet.py
flet/core/cupertino_button.py
flet/core/cupertino_checkbox.py
flet/core/cupertino_colors.py
flet/core/cupertino_context_menu.py
flet/core/cupertino_context_menu_action.py
flet/core/cupertino_date_picker.py
flet/core/cupertino_dialog_action.py
flet/core/cupertino_filled_button.py
flet/core/cupertino_icons.py
flet/core/cupertino_list_tile.py
flet/core/cupertino_navigation_bar.py
flet/core/cupertino_picker.py
flet/core/cupertino_radio.py
flet-0.27.3.dist-info/METADATA
flet-0.27.3.dist-info/WHEEL
flet-0.27.3.dist-info/entry_points.txt
flet-0.27.3.dist-info/RECORD
