Metadata-Version: 2.3
Name: flet
Version: 0.27.3
Summary: Flet for Python - easily build interactive multi-platform apps in Python
License: Apache-2.0
Author: Appveyor Systems Inc.
Author-email: hello@flet.dev
Requires-Python: >=3.9
Classifier: License :: OSI Approved :: Apache Software License
Classifier: Programming Language :: Python :: 3
Classifier: Programming Language :: Python :: 3.9
Classifier: Programming Language :: Python :: 3.10
Classifier: Programming Language :: Python :: 3.11
Classifier: Programming Language :: Python :: 3.12
Classifier: Programming Language :: Python :: 3.13
Provides-Extra: all
Provides-Extra: cli
Provides-Extra: desktop
Provides-Extra: web
Requires-Dist: flet-cli (==0.27.3) ; extra == "all" or extra == "cli"
Requires-Dist: flet-desktop (==0.27.3) ; (platform_system == "Darwin" or platform_system == "Windows") and (extra == "all" or extra == "desktop")
Requires-Dist: flet-desktop-light (==0.27.3) ; platform_system == "Linux" and (extra == "all" or extra == "desktop")
Requires-Dist: flet-web (==0.27.3) ; extra == "all" or extra == "web"
Requires-Dist: httpx ; platform_system != "Pyodide"
Requires-Dist: oauthlib (>=3.2.2,<4.0.0) ; platform_system != "Pyodide"
Requires-Dist: repath (>=0.9.0,<0.10.0)
Project-URL: Documentation, https://flet.dev/docs
Project-URL: Homepage, https://flet.dev
Project-URL: Repository, https://github.com/flet-dev/flet
